txtimg/__init__.py
txtimg/txtimg.py
txtimg/fonts/Roboto-Regular.ttf
txtimg-0.0.9.dist-info/LICENSE
txtimg-0.0.9.dist-info/METADATA
txtimg-0.0.9.dist-info/WHEEL
txtimg-0.0.9.dist-info/top_level.txt
txtimg-0.0.9.dist-info/RECORD
