Metadata-Version: 2.1
Name: txtimg
Version: 0.0.9
Summary: A library to easily create text-based images (e.g. images that primarily contain text).
Home-page: https://github.com/yoongkang/txtimg
Author: Yoong Kang Lim
Author-email: yoongkang.lim@gmail.com
License: UNKNOWN
Platform: UNKNOWN
Classifier: Programming Language :: Python :: 3
Classifier: License :: OSI Approved :: MIT License
Classifier: Operating System :: OS Independent
Requires-Python: >=3.6
Requires-Dist: Pillow
